tasked/__init__.py
tasked/__main__.py
tests/__init__.py
tasked-0.0.1.dist-info/LICENSE
tasked-0.0.1.dist-info/METADATA
tasked-0.0.1.dist-info/WHEEL
tasked-0.0.1.dist-info/entry_points.txt
tasked-0.0.1.dist-info/top_level.txt
tasked-0.0.1.dist-info/RECORD
