Metadata-Version: 2.1
Name: tasked
Version: 0.0.1
Summary: Cool Python app built with Pyrustic
Home-page: https://pyrustic.github.com
Author: Pyrustic Evangelist
Author-email: rusticalex@yahoo.com
Maintainer: Pyrustic Evangelist
Maintainer-email: rusticalex@yahoo.com
License: MIT
Keywords: application,pyrustic
Platform: UNKNOWN
Classifier: Programming Language :: Python :: 3
Classifier: License :: OSI Approved :: MIT License
Classifier: Operating System :: OS Independent
Requires-Python: >=3.5
License-File: LICENSE
Requires-Dist: shared
Requires-Dist: backstage
